vroom/job.py
vroom/location.py
vroom/amount.py
vroom/__init__.py
vroom/break_.py
vroom/vehicle.py
vroom/time_window.py
vroom/_vroom.cpython-311-aarch64-linux-gnu.so
vroom/solution/solution.py
vroom/solution/__init__.py
vroom/input/vehicle_step.py
vroom/input/input.py
vroom/input/__init__.py
vroom/input/forced_service.py
pyvroomwheels.libs/libcrypto-13880bfc.so.1.0.2k
pyvroomwheels.libs/libselinux-ae24b712.so.1
pyvroomwheels.libs/libssl-e50c59ab.so.1.0.2k
pyvroomwheels.libs/libgssapi_krb5-fec99a71.so.2.2
pyvroomwheels.libs/libkrb5-90a0ef7c.so.3.3
pyvroomwheels.libs/libcom_err-057ba42b.so.2.1
pyvroomwheels.libs/libkeyutils-19c64d08.so.1.5
pyvroomwheels.libs/libpcre-6b975b27.so.1.2.0
pyvroomwheels.libs/libk5crypto-47ac5e52.so.3.1
pyvroomwheels.libs/libkrb5support-73f3f43d.so.0.1
pyvroomwheels-1.13.5.dist-info/RECORD
pyvroomwheels-1.13.5.dist-info/WHEEL
pyvroomwheels-1.13.5.dist-info/entry_points.txt
pyvroomwheels-1.13.5.dist-info/LICENSE
pyvroomwheels-1.13.5.dist-info/METADATA
pyvroomwheels-1.13.5.dist-info/top_level.txt
