Metadata-Version: 2.1
Name: pyvroomwheels
Version: 1.13.5
Summary: Vehicle routing open-source optimization machine (VROOM)
Author: Jonathan Feinberg
Author-email: jonathf@gmail.com
License: BSD 2-Clause License
Classifier: License :: OSI Approved :: BSD License
Classifier: Programming Language :: Python :: 3
Requires-Python: >=3.7
License-File: LICENSE
Requires-Dist: numpy
Requires-Dist: pandas
